{
  "positions": [
    {
      "symbol": "CVS",
      "qty": 27.0,
      "avg_entry_price": 75.8286,
      "current_price": 110.4909,
      "market_value": 2983.2543,
      "unrealized_pl": 935.8821,
      "unrealized_plpc": 45.71,
      "side": "PositionSide.LONG"
    },
    {
      "symbol": "NVDA",
      "qty": 7.0,
      "avg_entry_price": 204.683386,
      "current_price": 206.67,
      "market_value": 1446.69,
      "unrealized_pl": 13.906298,
      "unrealized_plpc": 0.97,
      "side": "PositionSide.LONG"
    },
    {
      "symbol": "AAPL",
      "qty": 3.0,
      "avg_entry_price": 326.3367,
      "current_price": 325.25,
      "market_value": 975.75,
      "unrealized_pl": -3.2601,
      "unrealized_plpc": -0.33,
      "side": "PositionSide.LONG"
    },
    {
      "symbol": "AVGO",
      "qty": 2.0,
      "avg_entry_price": 372.44,
      "current_price": 385.66,
      "market_value": 771.32,
      "unrealized_pl": 26.44,
      "unrealized_plpc": 3.55,
      "side": "PositionSide.LONG"
    },
    {
      "symbol": "GE",
      "qty": 2.0,
      "avg_entry_price": 285.9889,
      "current_price": 341.0,
      "market_value": 682.0,
      "unrealized_pl": 110.0222,
      "unrealized_plpc": 19.23,
      "side": "PositionSide.LONG"
    },
    {
      "symbol": "TJX",
      "qty": 4.0,
      "avg_entry_price": 159.0,
      "current_price": 154.6,
      "market_value": 618.4,
      "unrealized_pl": -17.6,
      "unrealized_plpc": -2.77,
      "side": "PositionSide.LONG"
    },
    {
      "symbol": "SYY",
      "qty": 5.0,
      "avg_entry_price": 73.2124,
      "current_price": 81.22,
      "market_value": 406.1,
      "unrealized_pl": 40.038,
      "unrealized_plpc": 10.94,
      "side": "PositionSide.LONG"
    },
    {
      "symbol": "GD",
      "qty": 1.0,
      "avg_entry_price": 359.715,
      "current_price": 367.73,
      "market_value": 367.73,
      "unrealized_pl": 8.015,
      "unrealized_plpc": 2.23,
      "side": "PositionSide.LONG"
    },
    {
      "symbol": "UNH",
      "qty": 0.689655172,
      "avg_entry_price": 290.0,
      "current_price": 436.712,
      "market_value": 301.180689,
      "unrealized_pl": 101.180689,
      "unrealized_plpc": 50.59,
      "side": "PositionSide.LONG"
    },
    {
      "symbol": "D",
      "qty": 4.0,
      "avg_entry_price": 68.82,
      "current_price": 69.85,
      "market_value": 279.4,
      "unrealized_pl": 4.12,
      "unrealized_plpc": 1.5,
      "side": "PositionSide.LONG"
    },
    {
      "symbol": "BTCUSD",
      "qty": 0.003449908,
      "avg_entry_price": 70867.17,
      "current_price": 66319.951,
      "market_value": 228.79773,
      "unrealized_pl": -15.687487,
      "unrealized_plpc": -6.42,
      "side": "PositionSide.LONG"
    },
    {
      "symbol": "NBIS",
      "qty": 1.0,
      "avg_entry_price": 195.76,
      "current_price": 219.14,
      "market_value": 219.14,
      "unrealized_pl": 23.38,
      "unrealized_plpc": 11.94,
      "side": "PositionSide.LONG"
    },
    {
      "symbol": "737CVR019",
      "qty": 4.064262182,
      "avg_entry_price": 0.0,
      "current_price": 0.0,
      "market_value": 0.0,
      "unrealized_pl": 0.0,
      "unrealized_plpc": 0.0,
      "side": "PositionSide.LONG"
    }
  ],
  "totals": {
    "total_value": 9279.76,
    "total_pl": 1226.44,
    "total_plpc": 15.23,
    "position_count": 13,
    "updated_at": "2026-07-21T22:09:03.798577+00:00"
  },
  "account": {
    "cash": 21814.91,
    "portfolio_value": 31094.67,
    "buying_power": 111988.75
  }
}