{
  "positions": [
    {
      "symbol": "CVS",
      "qty": 27.0,
      "avg_entry_price": 75.8286,
      "current_price": 95.93,
      "market_value": 2590.11,
      "unrealized_pl": 542.7378,
      "unrealized_plpc": 26.51,
      "side": "PositionSide.LONG"
    },
    {
      "symbol": "NUE",
      "qty": 9.0,
      "avg_entry_price": 223.0,
      "current_price": 254.39,
      "market_value": 2289.51,
      "unrealized_pl": 282.51,
      "unrealized_plpc": 14.08,
      "side": "PositionSide.LONG"
    },
    {
      "symbol": "CCI",
      "qty": 20.0,
      "avg_entry_price": 84.31,
      "current_price": 94.49,
      "market_value": 1889.8,
      "unrealized_pl": 203.6,
      "unrealized_plpc": 12.07,
      "side": "PositionSide.LONG"
    },
    {
      "symbol": "NVDA",
      "qty": 7.0,
      "avg_entry_price": 212.129057,
      "current_price": 205.1,
      "market_value": 1435.7,
      "unrealized_pl": -49.203399,
      "unrealized_plpc": -3.31,
      "side": "PositionSide.LONG"
    },
    {
      "symbol": "TSM",
      "qty": 2.0,
      "avg_entry_price": 431.2689,
      "current_price": 415.17,
      "market_value": 830.34,
      "unrealized_pl": -32.1978,
      "unrealized_plpc": -3.73,
      "side": "PositionSide.LONG"
    },
    {
      "symbol": "GE",
      "qty": 2.0,
      "avg_entry_price": 285.9889,
      "current_price": 328.0,
      "market_value": 656.0,
      "unrealized_pl": 84.0222,
      "unrealized_plpc": 14.69,
      "side": "PositionSide.LONG"
    },
    {
      "symbol": "BA",
      "qty": 3.0,
      "avg_entry_price": 220.3292,
      "current_price": 215.45,
      "market_value": 646.35,
      "unrealized_pl": -14.6376,
      "unrealized_plpc": -2.21,
      "side": "PositionSide.LONG"
    },
    {
      "symbol": "TJX",
      "qty": 4.0,
      "avg_entry_price": 159.0,
      "current_price": 160.71,
      "market_value": 642.84,
      "unrealized_pl": 6.84,
      "unrealized_plpc": 1.07,
      "side": "PositionSide.LONG"
    },
    {
      "symbol": "SYY",
      "qty": 5.0,
      "avg_entry_price": 73.2124,
      "current_price": 76.29,
      "market_value": 381.45,
      "unrealized_pl": 15.388,
      "unrealized_plpc": 4.2,
      "side": "PositionSide.LONG"
    },
    {
      "symbol": "DXCM",
      "qty": 4.0,
      "avg_entry_price": 64.854,
      "current_price": 72.86,
      "market_value": 291.44,
      "unrealized_pl": 32.024,
      "unrealized_plpc": 12.35,
      "side": "PositionSide.LONG"
    },
    {
      "symbol": "UNH",
      "qty": 0.689655172,
      "avg_entry_price": 290.0,
      "current_price": 399.47,
      "market_value": 275.496552,
      "unrealized_pl": 75.496552,
      "unrealized_plpc": 37.75,
      "side": "PositionSide.LONG"
    },
    {
      "symbol": "PANW",
      "qty": 1.0,
      "avg_entry_price": 278.8085,
      "current_price": 272.05,
      "market_value": 272.05,
      "unrealized_pl": -6.7585,
      "unrealized_plpc": -2.42,
      "side": "PositionSide.LONG"
    },
    {
      "symbol": "D",
      "qty": 4.0,
      "avg_entry_price": 68.82,
      "current_price": 66.9,
      "market_value": 267.6,
      "unrealized_pl": -7.68,
      "unrealized_plpc": -2.79,
      "side": "PositionSide.LONG"
    },
    {
      "symbol": "BTCUSD",
      "qty": 0.003449908,
      "avg_entry_price": 70867.17,
      "current_price": 62175.93,
      "market_value": 214.501238,
      "unrealized_pl": -29.983979,
      "unrealized_plpc": -12.26,
      "side": "PositionSide.LONG"
    },
    {
      "symbol": "CSCO",
      "qty": 1.0,
      "avg_entry_price": 117.3405,
      "current_price": 121.64,
      "market_value": 121.64,
      "unrealized_pl": 4.2995,
      "unrealized_plpc": 3.66,
      "side": "PositionSide.LONG"
    },
    {
      "symbol": "737CVR019",
      "qty": 4.064262182,
      "avg_entry_price": 0.0,
      "current_price": 0.0,
      "market_value": 0.0,
      "unrealized_pl": 0.0,
      "unrealized_plpc": 0.0,
      "side": "PositionSide.LONG"
    }
  ],
  "totals": {
    "total_value": 12804.83,
    "total_pl": 1106.46,
    "total_plpc": 9.46,
    "position_count": 16,
    "updated_at": "2026-06-07T22:13:13.307389+00:00"
  },
  "account": {
    "cash": 18404.37,
    "portfolio_value": 31209.2,
    "buying_power": 108870.39
  }
}