{
  "positions": [
    {
      "symbol": "NVDA",
      "qty": 12.0,
      "avg_entry_price": 177.28225,
      "current_price": 176.8499,
      "market_value": 2122.1988,
      "unrealized_pl": -5.1882,
      "unrealized_plpc": -0.24,
      "side": "PositionSide.LONG"
    },
    {
      "symbol": "PANW",
      "qty": 12.0,
      "avg_entry_price": 160.15,
      "current_price": 162.9563,
      "market_value": 1955.4756,
      "unrealized_pl": 33.6756,
      "unrealized_plpc": 1.75,
      "side": "PositionSide.LONG"
    },
    {
      "symbol": "NKE",
      "qty": 44.0,
      "avg_entry_price": 45.2868,
      "current_price": 43.9969,
      "market_value": 1935.8636,
      "unrealized_pl": -56.7556,
      "unrealized_plpc": -2.85,
      "side": "PositionSide.LONG"
    },
    {
      "symbol": "DDOG",
      "qty": 16.0,
      "avg_entry_price": 119.0,
      "current_price": 120.15,
      "market_value": 1922.4,
      "unrealized_pl": 18.4,
      "unrealized_plpc": 0.97,
      "side": "PositionSide.LONG"
    },
    {
      "symbol": "CEG",
      "qty": 7.0,
      "avg_entry_price": 280.0,
      "current_price": 272.75,
      "market_value": 1909.25,
      "unrealized_pl": -50.75,
      "unrealized_plpc": -2.59,
      "side": "PositionSide.LONG"
    },
    {
      "symbol": "BTCUSD",
      "qty": 0.003449908,
      "avg_entry_price": 70867.17,
      "current_price": 66737.92,
      "market_value": 230.239684,
      "unrealized_pl": -14.245533,
      "unrealized_plpc": -5.83,
      "side": "PositionSide.LONG"
    },
    {
      "symbol": "UNH",
      "qty": 0.689655172,
      "avg_entry_price": 290.0,
      "current_price": 277.32,
      "market_value": 191.255172,
      "unrealized_pl": -8.744828,
      "unrealized_plpc": -4.37,
      "side": "PositionSide.LONG"
    },
    {
      "symbol": "737CVR019",
      "qty": 4.064262182,
      "avg_entry_price": 0.0,
      "current_price": 0.0,
      "market_value": 0.0,
      "unrealized_pl": 0.0,
      "unrealized_plpc": 0.0,
      "side": "PositionSide.LONG"
    }
  ],
  "totals": {
    "total_value": 10266.68,
    "total_pl": -83.61,
    "total_plpc": -0.81,
    "position_count": 8,
    "updated_at": "2026-04-02T21:49:23.609619+00:00"
  },
  "account": {
    "cash": 10681.38,
    "portfolio_value": 20948.06,
    "buying_power": 31399.2
  }
}